instagramreport/__init__.py
instagramreport/reportmaker.py
instagramreport-0.1.2.dist-info/METADATA
instagramreport-0.1.2.dist-info/RECORD
instagramreport-0.1.2.dist-info/WHEEL
instagramreport-0.1.2.dist-info/entry_points.txt
instagramreport-0.1.2.dist-info/top_level.txt
