Metadata-Version: 2.1
Name: instagramreport
Version: 0.1.2
Summary: App for creating an Instagram Business account performance report (in spanish)
Home-page: https://github.com/corvalanlara/
Author: Daniel Corvalán
Author-email: corvalanlara@protonmail.com
License: UNKNOWN
Platform: UNKNOWN
Classifier: Programming Language :: Python :: 3
Classifier: License :: OSI Approved :: GNU General Public License v3 (GPLv3)
Classifier: Operating System :: OS Independent
Classifier: Development Status :: 3 - Alpha
Requires-Dist: python-docx
Requires-Dist: certifi
Requires-Dist: facebook-sdk
Requires-Dist: requests
Requires-Dist: urllib3
